CONTRIBUTING.rst
MANIFEST.in
README.rst
requirements.txt
setup.cfg
setup.py
bioconvert/__init__.py
bioconvert/abi2fasta.py
bioconvert/abi2fastq.py
bioconvert/abi2qual.py
bioconvert/bam2bedgraph.py
bioconvert/bam2bigwig.py
bioconvert/bam2cov.py
bioconvert/bam2cram.py
bioconvert/bam2fasta.py
bioconvert/bam2fastq.py
bioconvert/bam2json.py
bioconvert/bam2sam.py
bioconvert/bam2tsv.py
bioconvert/bam2wiggle.py
bioconvert/bcf2vcf.py
bioconvert/bcf2wiggle.py
bioconvert/bed2wiggle.py
bioconvert/bedgraph2bigwig.py
bioconvert/bedgraph2cov.py
bioconvert/bedgraph2wiggle.py
bioconvert/bigbed2bed.py
bioconvert/bigbed2wiggle.py
bioconvert/bigwig2bedgraph.py
bioconvert/bigwig2wiggle.py
bioconvert/bplink2plink.py
bioconvert/bplink2vcf.py
bioconvert/bz22gz.py
bioconvert/clustal2fasta.py
bioconvert/clustal2nexus.py
bioconvert/clustal2phylip.py
bioconvert/clustal2stockholm.py
bioconvert/cram2bam.py
bioconvert/cram2fasta.py
bioconvert/cram2fastq.py
bioconvert/cram2sam.py
bioconvert/csv2tsv.py
bioconvert/csv2xls.py
bioconvert/dsrc2gz.py
bioconvert/embl2fasta.py
bioconvert/embl2genbank.py
bioconvert/fast52pod5.py
bioconvert/fasta2clustal.py
bioconvert/fasta2faa.py
bioconvert/fasta2fasta_agp.py
bioconvert/fasta2fastq.py
bioconvert/fasta2genbank.py
bioconvert/fasta2nexus.py
bioconvert/fasta2phylip.py
bioconvert/fasta2twobit.py
bioconvert/fasta_qual2fastq.py
bioconvert/fastq2fasta.py
bioconvert/fastq2fasta_qual.py
bioconvert/fastq2qual.py
bioconvert/genbank2embl.py
bioconvert/genbank2fasta.py
bioconvert/genbank2gff3.py
bioconvert/gfa2fasta.py
bioconvert/gff22gff3.py
bioconvert/gff32gff2.py
bioconvert/gff32gtf.py
bioconvert/gtf22gff3.py
bioconvert/gz2bz2.py
bioconvert/gz2dsrc.py
bioconvert/json2yaml.py
bioconvert/maf2sam.py
bioconvert/newick2nexus.py
bioconvert/newick2phyloxml.py
bioconvert/nexus2clustal.py
bioconvert/nexus2fasta.py
bioconvert/nexus2newick.py
bioconvert/nexus2phylip.py
bioconvert/nexus2phyloxml.py
bioconvert/ods2csv.py
bioconvert/pdb2faa.py
bioconvert/phylip2clustal.py
bioconvert.egg-info/PKG-INFO
bioconvert.egg-info/SOURCES.txt
bioconvert.egg-info/dependency_links.txt
bioconvert.egg-info/entry_points.txt
bioconvert.egg-info/not-zip-safe
bioconvert.egg-info/requires.txt
bioconvert.egg-info/top_level.txt
