Metadata-Version: 2.1
Name: bioconvert
Version: 1.1.1
Summary: convert between bioinformatics formats
Home-page: https://github.com/bioconvert/bioconvert
Author: The bioconvert Contributors
Author-email: thomas.cokelaer@pasteur.fr
Maintainer: Thomas Cokelaer
Maintainer-email: thomas.cokelaer@pasteur.fr
License: GPLv3
Download-URL: https://github.com/bioconvert/bioconvert
Keywords: NGS,bam2bed,fastq2fasta,bam2sam,conversion
Platform: Linux
Platform: Unix
Platform: MacOsX
Platform: Windows
Classifier: Development Status :: 5 - Production/Stable
Classifier: Intended Audience :: Developers
Classifier: Intended Audience :: Science/Research
Classifier: License :: OSI Approved :: GNU General Public License v3 (GPLv3)
Classifier: Operating System :: OS Independent
Classifier: Programming Language :: Python :: 3
Classifier: Programming Language :: Python :: 3.8
Classifier: Programming Language :: Python :: 3.9
Classifier: Programming Language :: Python :: 3.10
Classifier: Topic :: Software Development :: Libraries :: Python Modules
Classifier: Topic :: Scientific/Engineering :: Bio-Informatics
Classifier: Topic :: Scientific/Engineering :: Information Analysis
Provides-Extra: testing
Provides-Extra: doc
